[
  {
    "username": "atabakd",
    "tutorials": [],
    "assignments": [
      {
        "name": "assignment_git-atabakd",
        "status": ":white_check_mark:",
        "last_commit_date": "2018-02-06 11:31:52 UTC",
        "score": 3
      }
    ],
    "score": 3
  },
  {
    "username": "PCH313",
    "tutorials": [],
    "assignments": [
      {
        "name": "assignment_git-PCH313",
        "status": ":white_check_mark:",
        "last_commit_date": "2018-02-06 11:24:09 UTC",
        "score": 3
      }
    ],
    "score": 3
  },
  {
    "username": "prashanthr05",
    "tutorials": [],
    "assignments": [
      {
        "name": "assignment_git-prashanthr05",
        "status": ":white_check_mark:",
        "last_commit_date": "2018-02-06 11:30:08 UTC",
        "score": 3
      }
    ],
    "score": 3
  },
  {
    "username": "ninja777",
    "tutorials": [],
    "assignments": [
      {
        "name": "assignment_git-ninja777",
        "status": ":white_check_mark:",
        "last_commit_date": "2018-02-06 11:19:58 UTC",
        "score": 3
      }
    ],
    "score": 3
  },
  {
    "username": "osm3000",
    "tutorials": [],
    "assignments": [
      {
        "name": "assignment_git-osm3000",
        "status": ":white_check_mark:",
        "last_commit_date": "2018-02-06 11:15:12 UTC",
        "score": 3
      }
    ],
    "score": 3
  },
  {
    "username": "mkthabet",
    "tutorials": [],
    "assignments": [
      {
        "name": "assignment_git-mkthabet",
        "status": ":white_check_mark:",
        "last_commit_date": "2018-02-06 11:25:39 UTC",
        "score": 3
      }
    ],
    "score": 3
  },
  {
    "username": "Meylina",
    "tutorials": [],
    "assignments": [
      {
        "name": "assignment_git-Meylina",
        "status": ":white_check_mark:",
        "last_commit_date": "2018-02-06 11:23:50 UTC",
        "score": 3
      }
    ],
    "score": 3
  },
  {
    "username": "kosenhitatchi",
    "tutorials": [],
    "assignments": [
      {
        "name": "assignment_git-kosenhitatchi",
        "status": ":x:",
        "last_commit_date": "2018-01-13 16:26:00 UTC",
        "score": 1
      }
    ],
    "score": 0
  },
  {
    "username": "gonzalezJohnas",
    "tutorials": [],
    "assignments": [
      {
        "name": "assignment_git-gonzalezJohnas",
        "status": ":white_check_mark:",
        "last_commit_date": "2018-02-06 11:16:51 UTC",
        "score": 3
      }
    ],
    "score": 3
  },
  {
    "username": "anqingd",
    "tutorials": [],
    "assignments": [
      {
        "name": "assignment_git-anqingd",
        "status": ":x:",
        "last_commit_date": "2018-01-13 16:26:00 UTC",
        "score": 1
      }
    ],
    "score": 0
  },
  {
    "username": "ericpairet",
    "tutorials": [],
    "assignments": [
      {
        "name": "assignment_git-ericpairet",
        "status": ":x:",
        "last_commit_date": "2018-01-13 16:26:00 UTC",
        "score": 1
      }
    ],
    "score": 0
  },
  {
    "username": "jtalamini",
    "tutorials": [],
    "assignments": [
      {
        "name": "assignment_git-jtalamini",
        "status": ":white_check_mark:",
        "last_commit_date": "2018-02-06 11:20:41 UTC",
        "score": 3
      }
    ],
    "score": 3
  },
  {
    "username": "Rayne91",
    "tutorials": [],
    "assignments": [
      {
        "name": "assignment_git-Rayne91",
        "status": ":white_check_mark:",
        "last_commit_date": "2018-02-06 11:24:07 UTC",
        "score": 3
      }
    ],
    "score": 3
  },
  {
    "username": "jasonsiver",
    "tutorials": [],
    "assignments": [
      {
        "name": "assignment_git-jasonsiver",
        "status": ":x:",
        "last_commit_date": "2018-01-13 16:26:00 UTC",
        "score": 1
      }
    ],
    "score": 0
  },
  {
    "username": "JuanMiguelAlvarez",
    "tutorials": [],
    "assignments": [
      {
        "name": "assignment_git-JuanMiguelAlvarez",
        "status": ":white_check_mark:",
        "last_commit_date": "2018-02-06 11:29:52 UTC",
        "score": 3
      }
    ],
    "score": 3
  },
  {
    "username": "umgnunes",
    "tutorials": [],
    "assignments": [
      {
        "name": "assignment_git-umgnunes",
        "status": ":white_check_mark:",
        "last_commit_date": "2018-02-06 11:16:51 UTC",
        "score": 3
      }
    ],
    "score": 3
  },
  {
    "username": "samvinanzi",
    "tutorials": [],
    "assignments": [
      {
        "name": "assignment_git-samvinanzi",
        "status": ":white_check_mark:",
        "last_commit_date": "2018-02-06 11:26:36 UTC",
        "score": 3
      }
    ],
    "score": 3
  },
  {
    "username": "AbbasSidaoui",
    "tutorials": [],
    "assignments": [],
    "score": 0
  },
  {
    "username": "raedbsili1991",
    "tutorials": [],
    "assignments": [
      {
        "name": "assignment_git-raedbsili1991",
        "status": ":x:",
        "last_commit_date": "2018-01-13 16:26:00 UTC",
        "score": 1
      }
    ],
    "score": 0
  },
  {
    "username": "marco-monforte",
    "tutorials": [],
    "assignments": [
      {
        "name": "assignment_git-marco-monforte",
        "status": ":white_check_mark:",
        "last_commit_date": "2018-02-06 11:17:26 UTC",
        "score": 3
      }
    ],
    "score": 3
  },
  {
    "username": "njm12",
    "tutorials": [],
    "assignments": [],
    "score": 0
  },
  {
    "username": "UgoVollhardt",
    "tutorials": [],
    "assignments": [
      {
        "name": "assignment_git-UgoVollhardt",
        "status": ":white_check_mark:",
        "last_commit_date": "2018-02-06 11:43:26 UTC",
        "score": 3
      }
    ],
    "score": 3
  },
  {
    "username": "fbottarel",
    "tutorials": [],
    "assignments": [
      {
        "name": "assignment_git-fbottarel",
        "status": ":white_check_mark:",
        "last_commit_date": "2018-02-06 11:40:41 UTC",
        "score": 1
      }
    ],
    "score": 1
  },
  {
    "username": "nikmayr2",
    "tutorials": [],
    "assignments": [
      {
        "name": "assignment_git-nikmayr2",
        "status": ":white_check_mark:",
        "last_commit_date": "2018-02-06 11:26:28 UTC",
        "score": 3
      }
    ],
    "score": 3
  },
  {
    "username": "science-code",
    "tutorials": [],
    "assignments": [
      {
        "name": "assignment_git-science-code",
        "status": ":white_check_mark:",
        "last_commit_date": "2018-02-06 11:09:46 UTC",
        "score": 3
      }
    ],
    "score": 3
  },
  {
    "username": "yidiem",
    "tutorials": [],
    "assignments": [
      {
        "name": "assignment_git-yidiem",
        "status": ":white_check_mark:",
        "last_commit_date": "2018-02-06 11:23:43 UTC",
        "score": 3
      }
    ],
    "score": 3
  },
  {
    "username": "DonatiElisa",
    "tutorials": [],
    "assignments": [
      {
        "name": "assignment_git-DonatiElisa",
        "status": ":white_check_mark:",
        "last_commit_date": "2018-02-06 11:24:16 UTC",
        "score": 1
      }
    ],
    "score": 1
  }
]
